{
  "$schema": "https://developer.microsoft.com/json-schemas/fabric/item/report/definition/visualContainer/2.8.0/schema.json",
  "name": "1738fb7128ec449ef059",
  "position": {
    "x": 505.71022902648315,
    "y": 212.39829619112291,
    "z": 4000,
    "height": 148.34166718110171,
    "width": 234.31240611560386,
    "tabOrder": 4000
  },
  "visual": {
    "visualType": "cardVisual",
    "query": {
      "queryState": {
        "Data": {
          "projections": [
            {
              "field": {
                "Measure": {
                  "Expression": {
                    "SourceRef": {
                      "Entity": "_Measures"
                    }
                  },
                  "Property": "Sales YTD"
                }
              },
              "queryRef": "_Measures.Sales YTD",
              "nativeQueryRef": "Sales YTD"
            }
          ]
        }
      },
      "sortDefinition": {
        "sort": [
          {
            "field": {
              "Measure": {
                "Expression": {
                  "SourceRef": {
                    "Entity": "_Measures"
                  }
                },
                "Property": "Sales YTD"
              }
            },
            "direction": "Descending"
          }
        ],
        "isDefaultSort": true
      }
    },
    "objects": {
      "cardCalloutArea": [
        {
          "properties": {
            "show": {
              "expr": {
                "Literal": {
                  "Value": "true"
                }
              }
            },
            "backgroundFillColor": {
              "solid": {
                "color": {
                  "expr": {
                    "Literal": {
                      "Value": "'#252B3B'"
                    }
                  }
                }
              }
            }
          },
          "selector": {
            "id": "default"
          }
        }
      ],
      "label": [
        {
          "properties": {
            "fontFamily": {
              "expr": {
                "Literal": {
                  "Value": "'''Comic Sans MS'''"
                }
              }
            },
            "fontSize": {
              "expr": {
                "Literal": {
                  "Value": "11D"
                }
              }
            },
            "bold": {
              "expr": {
                "Literal": {
                  "Value": "true"
                }
              }
            },
            "fontColor": {
              "solid": {
                "color": {
                  "expr": {
                    "Literal": {
                      "Value": "'#A0AEC0'"
                    }
                  }
                }
              }
            }
          },
          "selector": {
            "id": "default"
          }
        }
      ],
      "value": [
        {
          "properties": {
            "fontFamily": {
              "expr": {
                "Literal": {
                  "Value": "'''Comic Sans MS'''"
                }
              }
            },
            "fontSize": {
              "expr": {
                "Literal": {
                  "Value": "28D"
                }
              }
            },
            "bold": {
              "expr": {
                "Literal": {
                  "Value": "true"
                }
              }
            },
            "fontColor": {
              "solid": {
                "color": {
                  "expr": {
                    "Literal": {
                      "Value": "'#4FACFE'"
                    }
                  }
                }
              }
            }
          },
          "selector": {
            "id": "default"
          }
        }
      ]
    },
    "visualContainerObjects": {
      "title": [
        {
          "properties": {
            "titleWrap": {
              "expr": {
                "Literal": {
                  "Value": "true"
                }
              }
            }
          }
        }
      ],
      "spacing": [
        {
          "properties": {
            "verticalSpacing": {
              "expr": {
                "Literal": {
                  "Value": "2D"
                }
              }
            }
          },
          "selector": {
            "id": "default"
          }
        }
      ],
      "background": [
        {
          "properties": {
            "show": {
              "expr": {
                "Literal": {
                  "Value": "true"
                }
              }
            },
            "color": {
              "solid": {
                "color": {
                  "expr": {
                    "Literal": {
                      "Value": "'#252B3B'"
                    }
                  }
                }
              }
            },
            "transparency": {
              "expr": {
                "Literal": {
                  "Value": "0D"
                }
              }
            }
          }
        }
      ],
      "border": [
        {
          "properties": {
            "show": {
              "expr": {
                "Literal": {
                  "Value": "true"
                }
              }
            },
            "color": {
              "solid": {
                "color": {
                  "expr": {
                    "Literal": {
                      "Value": "'#4FACFE'"
                    }
                  }
                }
              }
            },
            "radius": {
              "expr": {
                "Literal": {
                  "Value": "8D"
                }
              }
            },
            "width": {
              "expr": {
                "Literal": {
                  "Value": "1D"
                }
              }
            }
          }
        }
      ]
    },
    "drillFilterOtherVisuals": true
  }
}